hmy_pakage/__init__.py
hmy_pakage/calculator.py
minyeopheo-0.0.1.dist-info/METADATA
minyeopheo-0.0.1.dist-info/WHEEL
minyeopheo-0.0.1.dist-info/top_level.txt
minyeopheo-0.0.1.dist-info/RECORD
