Metadata-Version: 2.1
Name: minyeopheo
Version: 0.0.1
Summary: nice caluclator
Home-page: https://github.com/hmy7788/calc0001.git
Download-URL: https://github.com/hmy7788/calc0001.git
Author: myheominyeop
Classifier: Programming Language :: Python :: 3
